strategia/__init__.py
strategia-0.0.1.dist-info/LICENSE
strategia-0.0.1.dist-info/METADATA
strategia-0.0.1.dist-info/WHEEL
strategia-0.0.1.dist-info/top_level.txt
strategia-0.0.1.dist-info/RECORD
